mtvs/__init__.py
mtvs/version.py
mtvs-0.0.1.dist-info/LICENSE
mtvs-0.0.1.dist-info/METADATA
mtvs-0.0.1.dist-info/WHEEL
mtvs-0.0.1.dist-info/top_level.txt
mtvs-0.0.1.dist-info/zip-safe
mtvs-0.0.1.dist-info/RECORD
