Metadata-Version: 2.1
Name: mtvs
Version: 0.0.1
Summary: MeTaVerSe
Home-page: https://github.com/HaveTwoBrush/mtvs
Author: HaveTwoBrush
Author-email: kinggreenhall@163.com
License: MIT License
Platform: UNKNOWN
Classifier: Programming Language :: Python :: 3
Classifier: License :: OSI Approved :: MIT License
Classifier: Operating System :: OS Independent
Requires-Python: >=3.6
Requires-Dist: setuptools (>=40.6.3)
